picard/__init__.py
picard/afunctor.py
picard/api.py
picard/argparse.py
picard/aws.py
picard/clang.py
picard/context.py
picard/file.py
picard/functor.py
picard/pattern.py
picard/rule.py
picard/shell.py
picard/typing.py
picard.py-0.1.3.dist-info/LICENSE
picard.py-0.1.3.dist-info/WHEEL
picard.py-0.1.3.dist-info/METADATA
picard.py-0.1.3.dist-info/RECORD
